unstructured_platform/__init__.py
unstructured_platform/client.py
unstructured_platform/models.py
unstructured_platform/api/__init__.py
unstructured_platform/api/base.py
unstructured_platform/api/destinations.py
unstructured_platform/api/jobs.py
unstructured_platform/api/sources.py
unstructured_platform/api/workflows.py
unstructured_platform-0.4.3.dist-info/METADATA
unstructured_platform-0.4.3.dist-info/WHEEL
unstructured_platform-0.4.3.dist-info/licenses/LICENSE
unstructured_platform-0.4.3.dist-info/RECORD
